pycirce/__init__.py
pycirce-0.1.0.dist-info/LICENSE
pycirce-0.1.0.dist-info/METADATA
pycirce-0.1.0.dist-info/WHEEL
pycirce-0.1.0.dist-info/top_level.txt
pycirce-0.1.0.dist-info/RECORD
