Metadata-Version: 2.1
Name: pycirce
Version: 0.1.0
Summary: pycirce, a set of combinators for encoding and decoding data
Author-email: Devon Stewart <blast@hardchee.se>
Project-URL: Homepage, https://github.com/blast-hardcheese/pycirce
Project-URL: Issues, https://github.com/blast-hardcheese/pycirce/issues
Classifier: Programming Language :: Python :: 3
Classifier: License :: OSI Approved :: MIT License
Classifier: Operating System :: OS Independent
Requires-Python: >=3.9
License-File: LICENSE
